<PacketHandler-array>
		<PacketHandler>
			<ids>
				<int>1</int>
			</ids>
			<className>org.moparscape.msc.gs.phandler.ls.StatRequestHandler</className>
		</PacketHandler>
		<PacketHandler>
			<ids>
				<int>2</int>
			</ids>
			<className>org.moparscape.msc.gs.phandler.ls.PlayerListRequestHandler</className>
		</PacketHandler>
		<PacketHandler>
			<ids>
				<int>3</int>
			</ids>
			<className>org.moparscape.msc.gs.phandler.ls.ShutdownHandler</className>
		</PacketHandler>
		<PacketHandler>
			<ids>
				<int>4</int>
			</ids>
			<className>org.moparscape.msc.gs.phandler.ls.UpdateHandler</className>
		</PacketHandler>
		<PacketHandler>
			<ids>
				<int>5</int>
			</ids>
			<className>org.moparscape.msc.gs.phandler.ls.GlobalHandler</className>
		</PacketHandler>
		<PacketHandler>
			<ids>
				<int>6</int>
			</ids>
			<className>org.moparscape.msc.gs.phandler.ls.AlertHandler</className>
		</PacketHandler>
		<PacketHandler>
			<ids>
				<int>7</int>
			</ids>
			<className>org.moparscape.msc.gs.phandler.ls.ForceLogout</className>
		</PacketHandler>
		<PacketHandler>
			<ids>
				<int>8</int>
			</ids>
			<className>org.moparscape.msc.gs.phandler.ls.ReportInfoRequestHandler</className>
		</PacketHandler>
		<PacketHandler>
			<ids>
				<int>9</int>
			</ids>
			<className>org.moparscape.msc.gs.phandler.ls.PlayerInfoRequestHandler</className>
		</PacketHandler>
		<PacketHandler>
			<ids>
				<int>10</int>
			</ids>
			<className>org.moparscape.msc.gs.phandler.ls.ReceivePM</className>
		</PacketHandler>
		<PacketHandler>
			<ids>
				<int>11</int>
			</ids>
			<className>org.moparscape.msc.gs.phandler.ls.FriendLogin</className>
		</PacketHandler>
		<PacketHandler>
			<ids>
				<int>12</int>
				<int>13</int>
			</ids>
			<className>org.moparscape.msc.gs.phandler.ls.FriendLogout</className>
		</PacketHandler>
</PacketHandler-array>